giga/__init__.py
giga/__main__.py
giga/app.py
giga/cache.py
giga/client.py
giga/config.py
giga/role.py
giga/utils.py
giga/handlers/__init__.py
giga/handlers/chat_handler.py
giga/handlers/default_handler.py
giga/handlers/handler.py
giga/handlers/repl_handler.py
gigashell-0.9.4.3.dist-info/METADATA
gigashell-0.9.4.3.dist-info/WHEEL
gigashell-0.9.4.3.dist-info/entry_points.txt
gigashell-0.9.4.3.dist-info/licenses/LICENSE
gigashell-0.9.4.3.dist-info/RECORD
